pep/__init__.py
pep/pep.py
pep_reader/__init__.py
pep_reader/pep.py
pep_reader-0.1.1.dist-info/DESCRIPTION.rst
pep_reader-0.1.1.dist-info/METADATA
pep_reader-0.1.1.dist-info/RECORD
pep_reader-0.1.1.dist-info/WHEEL
pep_reader-0.1.1.dist-info/entry_points.txt
pep_reader-0.1.1.dist-info/metadata.json
pep_reader-0.1.1.dist-info/top_level.txt
